revoltlogger/__init__.py
revoltlogger/core.py
revoltlogger/levels.py
revoltlogger/themes.py
revoltlogger-1.0.1.dist-info/licenses/LICENSE
revoltlogger-1.0.1.dist-info/METADATA
revoltlogger-1.0.1.dist-info/WHEEL
revoltlogger-1.0.1.dist-info/top_level.txt
revoltlogger-1.0.1.dist-info/RECORD
