Metadata-Version: 2.4
Name: revoltlogger
Version: 1.0.1
Summary: RevoltLogger - A simple and colorful logging library for Python tools, CLI applications, and security automation.
Author-email: "D. Sanjai Kumar" <bughunterz0047@gmail.com>
License: MIT
Project-URL: Homepage, https://github.com/RevoltSecurities/revoltlogger
Project-URL: Documentation, https://github.com/RevoltSecurities/revoltlogger
Project-URL: Source, https://github.com/RevoltSecurities/revoltlogger
Project-URL: Issues, https://github.com/RevoltSecurities/revoltlogger/issues
Keywords: logger,logging,colorlogger,python-logger,penetration-testing,bugbounty,cli-tools,colorama
Classifier: Development Status :: 5 - Production/Stable
Classifier: Programming Language :: Python :: 3
Classifier: License :: OSI Approved :: MIT License
Classifier: Operating System :: OS Independent
Classifier: Intended Audience :: Developers
Classifier: Topic :: Software Development :: Libraries :: Python Modules
Classifier: Topic :: System :: Logging
Requires-Python: >=3.7
License-File: LICENSE
Requires-Dist: colorama>=0.4.6
Dynamic: license-file
